typer_injector/__init__.py
typer_injector/_inject.py
typer_injector/_typer_injector.py
typer_injector/_types.py
typer_injector/exceptions.py
typer_injector-0.1.1.dist-info/METADATA
typer_injector-0.1.1.dist-info/WHEEL
typer_injector-0.1.1.dist-info/licenses/LICENSE.txt
typer_injector-0.1.1.dist-info/RECORD
