Metadata-Version: 2.4
Name: typer-injector
Version: 0.1.1
Summary: Dependency injection for typer
Project-URL: Documentation, https://github.com/Benjy/typer-injector#readme
Project-URL: Issues, https://github.com/Benjy/typer-injector/issues
Project-URL: Source, https://github.com/Benjy/typer-injector
Author-email: Benjy Wiener <benjywiener@gmail.com>
License-Expression: MIT
License-File: LICENSE.txt
Classifier: Development Status :: 4 - Beta
Classifier: Programming Language :: Python
Classifier: Programming Language :: Python :: 3.10
Classifier: Programming Language :: Python :: 3.11
Classifier: Programming Language :: Python :: 3.12
Classifier: Programming Language :: Python :: 3.13
Classifier: Programming Language :: Python :: 3.14
Classifier: Programming Language :: Python :: Implementation :: CPython
Classifier: Programming Language :: Python :: Implementation :: PyPy
Requires-Python: >=3.10
Requires-Dist: typer>=0.20.0
Provides-Extra: dev
Requires-Dist: pytest; extra == 'dev'
